scrapy_requests_spider_closed/__init__.py
scrapy_requests_spider_closed/main.py
scrapy_requests_spider_closed-0.0.1.dist-info/LICENSE
scrapy_requests_spider_closed-0.0.1.dist-info/METADATA
scrapy_requests_spider_closed-0.0.1.dist-info/WHEEL
scrapy_requests_spider_closed-0.0.1.dist-info/top_level.txt
scrapy_requests_spider_closed-0.0.1.dist-info/RECORD
