Metadata-Version: 2.2
Name: scrapy-requests-spider-closed
Version: 0.0.1
Summary: scrapy-requests-spider-closed is an extension to make requests when the spider is closed
Author: Xavier Zambrano
License: Copyright (c) 2012-2024 Scott Chacon and others
Classifier: Programming Language :: Python :: 3
License-File: LICENSE
Requires-Dist: scrapy
Requires-Dist: requests
